pypkg_builder/__init__.py
pypkg_builder/app.py
pypkg_builder/license.py
pypkg_builder/readme.py
pypkg_builder/setuptoolfn.py
pypkg_builder/tree.py
pypkg_builder/templates/help.html
pypkg_builder/templates/index.html
pypkg_builder/types/Apache Version 2.0.txt
pypkg_builder/types/GNU GPLv3.txt
pypkg_builder/types/MIT License.txt
pypkg_builder/types/Mozilla Public License 2.0.txt
pypkg_builder/types/The Unlicense.txt
pypkg_builder/types/user_defined.txt
pypkg_builder-1.0.dist-info/METADATA
pypkg_builder-1.0.dist-info/WHEEL
pypkg_builder-1.0.dist-info/entry_points.txt
pypkg_builder-1.0.dist-info/top_level.txt
pypkg_builder-1.0.dist-info/RECORD
