Metadata-Version: 2.1
Name: pypkg-builder
Version: 1.0
Summary: A simple tool for packaging python
Home-page: https://github.com/dipson94/packagemaker
Author: Dipson
Classifier: License :: OSI Approved :: GNU General Public License v3 (GPLv3)
Classifier: Programming Language :: Python :: 3.10
Classifier: Operating System :: OS Independent
Requires-Python: >=3.10
Requires-Dist: pyperclip
Requires-Dist: flask
Requires-Dist: datetime
